weplot/__init__.py
weplot/figure.py
weplot/layout.py
weplot/plot.py
weplot/subplot.py
weplot/version.py
weplot-0.0.9.dist-info/METADATA
weplot-0.0.9.dist-info/RECORD
weplot-0.0.9.dist-info/WHEEL
weplot-0.0.9.dist-info/top_level.txt
