Metadata-Version: 2.1
Name: weplot
Version: 0.0.9
Summary: An easy to use plotly wrapper for python / jupyter notebooks
Home-page: https://github.com/arraystream/weplot
Author: ArrayStream (Yu Zheng, Ran Fan)
Author-email: team@arraystream.com
License: MIT
Platform: any
Classifier: Development Status :: 4 - Beta
Classifier: Programming Language :: Python :: 3
Classifier: Programming Language :: Python :: 3.3
Classifier: Programming Language :: Python :: 3.4
Classifier: Programming Language :: Python :: 3.5
Classifier: Topic :: Scientific/Engineering :: Visualization
Requires-Dist: plotly
